MainHash/__algs.py
MainHash/__init__.py
MainHash/all.py
MainHash/blake2b.py
MainHash/blake2s.py
MainHash/md5.py
MainHash/script.py
MainHash/sha1.py
MainHash/sha224.py
MainHash/sha256.py
MainHash/sha384.py
MainHash/sha3_224.py
MainHash/sha3_256.py
MainHash/sha3_384.py
MainHash/sha3_512.py
MainHash/sha512.py
mainhash-0.0.10.dist-info/METADATA
mainhash-0.0.10.dist-info/WHEEL
mainhash-0.0.10.dist-info/entry_points.txt
mainhash-0.0.10.dist-info/RECORD
