Metadata-Version: 2.1
Name: mainhash
Version: 0.0.10
Summary: Simplifying checksum generation
Home-page: https://github.com/MainPlay-TG/MainHash.py
Author: MainPlay TG
Author-email: xbox.roman6666666666@gmail.com
Requires-Python: >=3.8,<4.0
Classifier: Programming Language :: Python :: 3
Classifier: Programming Language :: Python :: 3.8
Classifier: Programming Language :: Python :: 3.9
Classifier: Programming Language :: Python :: 3.10
Classifier: Programming Language :: Python :: 3.11
Classifier: Programming Language :: Python :: 3.12
Requires-Dist: mainshortcuts (>=1.5.7,<2.0.0)
Project-URL: Repository, https://github.com/MainPlay-TG/MainHash.py
